autodistill_blip/__init__.py
autodistill_blip/blip.py
autodistill_blip-0.1.3.dist-info/LICENSE
autodistill_blip-0.1.3.dist-info/METADATA
autodistill_blip-0.1.3.dist-info/WHEEL
autodistill_blip-0.1.3.dist-info/top_level.txt
autodistill_blip-0.1.3.dist-info/RECORD
